{
    "demographics": {
        "category": {
            "aboutMe": {
                "birthday": {
                    "question": "Quelle est votre date de naissance ?",
                    "shortName": "Date de naissance"
                },
                "country": {
                    "question": "Dans quel pays vivez-vous ?",
                    "shortName": "Pays"
                },
                "gender": {
                    "question": "À quel genre vous identifiez-vous ?",
                    "shortName": "Genre"
                },
                "postalCode": {
                    "question": "Quel est votre code postal ?",
                    "shortName": "Code postal"
                },
                "hispanic": {
                    "question": "Êtes-vous d'origine hispanique, latine ou espagnole ?",
                    "shortName": "Hispanique, Latino, ou d'origine espagnole"
                },
                "ethnicity_us": {
                    "list": {
                        "white": "Blanc",
                        "black": "Noir ou Afro-américain",
                        "indian": "Amérindien ou Autochtone d'Alaska",
                        "asian": "Asiatique",
                        "islander": "Insulaire du Pacifique ou Autochtone hawaïen",
                        "other": "Autre"
                    }
                },
                "ethnicity_gb": {
                    "list": {
                        "white": "Blanc",
                        "traveller": "Traveller / Traveller irlandais",
                        "asian_indian": "Asiatique ou Britannique asiatique : Indien",
                        "asian_pakistani": "Asiatique ou Britannique asiatique : Pakistanais",
                        "asian_bangladeshi": "Asiatique ou Britannique asiatique : Bangladais",
                        "asian_chinese": "Asiatique ou Britannique asiatique : Chinois",
                        "asian_other": "Asiatique ou Britannique asiatique : Autre origine asiatique",
                        "black": "Noir ou Britannique noir",
                        "mixed": "Mixte ou Multiple"
                    }
                },
                "householdDescription": {
                    "list": {
                        "cohabiting": "Union libre / Concubinage",
                        "single": "Célibataire, jamais marié·e",
                        "married": "Marié·e",
                        "divorced": "Divorcé·e",
                        "separated": "Séparé·e",
                        "widowed": "Veuf·ve"
                    },
                    "question": "Quelle est votre situation familiale ?",
                    "shortName": "Situation familiale"
                },
                "education_us": {
                    "list": {
                        "no_hs_diploma": "Quelques années d'études secondaires ou moins",
                        "hs_or_ged": "Diplôme d'études secondaires ou équivalent",
                        "some_college": "Quelques années d'études universitaires, sans diplôme",
                        "two_year_degree": "Diplôme universitaire – Associate Degree (2 ans)",
                        "four_year_degree": "Diplôme universitaire – Licence (4 ans)",
                        "post_grad_degree": "Diplôme d'études supérieures – MS, MA, MBA, PhD, etc.",
                        "professional_degree": "Diplôme professionnel – MD, DVM, DDS, etc."
                    }
                },
                "languages": {
                    "question": "Quelles langues parlez-vous et dans lesquelles vous sentez-vous à l'aise pour donner votre avis ?",
                    "list": {
                        "arabic": "Arabe",
                        "basque": "Basque",
                        "berber": "Berbère",
                        "bulgarian": "Bulgare",
                        "catalan": "Catalan",
                        "chinese": "Chinois",
                        "croatian": "Croate",
                        "czech": "Tchèque",
                        "danish": "Danois",
                        "dutch": "Néerlandais",
                        "english": "Anglais",
                        "estonian": "Estonien",
                        "finnish": "Finlandais",
                        "french": "Français",
                        "galician": "Galicien",
                        "german": "Allemand",
                        "greek": "Grec",
                        "hindi": "Hindi",
                        "hungarian": "Hongrois",
                        "italian": "Italien",
                        "irish": "Irlandais",
                        "latvian": "Letton",
                        "lithuanian": "Lituanien",
                        "japanese": "Japonais",
                        "kurdish": "Kurde",
                        "korean": "Coréen",
                        "maltese": "Maltais",
                        "norwegian": "Norvégien",
                        "polish": "Polonais",
                        "portuguese": "Portugais",
                        "romanian": "Roumain",
                        "punjabi": "Pendjabi",
                        "russian": "Russe",
                        "scottish": "Écossais",
                        "slovak": "Slovaque",
                        "slovenian": "Slovène",
                        "spanish": "Espagnol",
                        "swedish": "Suédois",
                        "tagalog": "Tagalog",
                        "tamil": "Tamoul",
                        "turkish": "Turc",
                        "urdu": "Ourdou",
                        "welsh": "Gallois"
                    },
                    "shortName": "Langues que vous parlez et dans lesquelles vous vous sentez à l'aise pour donner votre avis"
                },
                "education_es": {
                    "list": {
                        "lessHighschool": "Enseignement secondaire obligatoire ou moins",
                        "highschool": "Diplôme de l'enseignement secondaire obligatoire (E.S.O)",
                        "technical": "Diplôme technique / professionnel",
                        "someBaccalaureate": "Quelques années d’enseignement secondaire supérieur (baccalauréat espagnol)",
                        "baccalaureate": "Diplôme d'enseignement secondaire supérieur (baccalauréat espagnol)",
                        "someCollege": "Quelques années d'études universitaires",
                        "college": "Diplôme universitaire (3 ans)",
                        "masters": "Master",
                        "phd": "Doctorat"
                    }
                },
                "education_gb": {
                    "list": {
                        "junior_infant": "École primaire et maternelle combinées/Infant School Junior School",
                        "comprehensive": "École polyvalente (GCSE)/Secondaire moderne (GCSE)/École secondaire (GCSE)/Collège technologique (GCSE)/Sixth Form",
                        "college": "Collège universitaire/Institution d'enseignement supérieur",
                        "open_college": "Collège universitaire ouvert - Collège universitaire de technologie - Institut / Université de formation des enseignants",
                        "junior": "Junior School",
                        "university": "Université / Université ouverte",
                        "some_college": "Quelques années d'études universitaires, sans diplôme"
                    }
                },
                "education_de": {
                    "list": {
                        "primary": "École primaire",
                        "medium": "Instruction moyenne (lycée / MSA, etc.)",
                        "university": "Abitur (baccalauréat Allemand) / Université",
                        "associate": "Associate degree (2 ans)",
                        "secondaryOther": "Autre deuxième cycle de l'enseignement secondaire achevé",
                        "diploma": "Diplôme (FH / DH)",
                        "bachelor": "Licence",
                        "magister": "Magister",
                        "master": "Master",
                        "phd": "Doctorat",
                        "universityOther": "Autre diplôme universitaire"
                    }
                },
                "education_au": {
                    "list": {
                        "furtherqualification": "Supérieur (entre le lycée et l'université)",
                        "universityNoDegree": "Quelques années d'études universitaires, sans diplôme",
                        "universityDegree": "Diplôme universitaire",
                        "master": "Master ou diplôme professionnel",
                        "doctorate": "Doctorat",
                        "belowGcse": "Inférieur au GCSE",
                        "gcse": "GCSE ou équivalent",
                        "alevel": "A-levels ou équivalent"
                    }
                },
                "education_at": {
                    "list": {
                        "not_lower_secondary": "Quelques années du premier cycle du secondaire/gymnasium (lycée)",
                        "lower_secondary": "Certificat d'études secondaires du premier cycle/gymnasium (lycée)",
                        "vocational": "Certificat de la Berufsschule (école professionnelle)",
                        "higher_technical": "Certificat de Höhere Schule",
                        "university": "Diplôme universitaire",
                        "master": "Master",
                        "phd": "Doctorat"
                    }
                },
                "education_ie": {
                    "list": {
                        "post_primary": "Enseignement post-primaire ou moins",
                        "leaving": "Diplôme de fin d'études",
                        "third_level": "Quelques années d'études de troisième cycle, sans diplôme",
                        "higher_technical": "Diplôme d'études supérieures",
                        "bachelor": "Licence",
                        "master": "Master ou diplôme professionnel",
                        "phd": "Doctorat",
                        "post_leaving": "Diplôme de fin d'études - formation professionnelle"
                    }
                },
                "education_dk": {
                    "list": {
                        "primary": "École publique (école primaire et secondaire du premier cycle)",
                        "secondary": "A-levels / lycée (école secondaire de deuxième cycle)",
                        "vocational": "Ouvrier qualifié / ouvrier ou autre formation professionnelle",
                        "uncompleted_tertiary": "Études universitaires, sans diplôme",
                        "first_degree": "Programme de premier cycle de 2 ans / mineure universitaire",
                        "bachelor": "Licence",
                        "master": "Master",
                        "phd": "Doctorat"
                    }
                },
                "education_mx": {
                    "list": {
                        "incomplete_prep": "École préparatoire incomplète ou moins",
                        "prep": "Diplôme de l'école préparatoire",
                        "vocational": "Études supérieures, école professionnelle",
                        "university": "Études universitaires, sans diplôme",
                        "technical": "Diplôme technique ou commercial",
                        "undergraduate": "Diplôme de premier cycle",
                        "master": "Master ou diplôme professionnel",
                        "phd": "Doctorat"
                    }
                },
                "education_se": {
                    "list": {
                        "some_a_level": "A-Levels ou moins",
                        "a_level": "A-Levels",
                        "vocational": "Autre qualification professionnelle de niveau post-secondaire",
                        "some_university": "Études universitaires, sans diplôme",
                        "university": "Diplôme universitaire (2 ans d'études)",
                        "bachelor": "Licence",
                        "master": "Master ou diplôme professionnel",
                        "phd": "Doctorat"
                    }
                },
                "education_nl": {
                    "list": {
                        "no_hs_diploma": "Niveau d'études secondaires ou moins",
                        "diploma": "Diplôme de fin d'études secondaires",
                        "technical": "Autre formation professionnelle après l'école secondaire",
                        "some_college": "Quelques années d'études en sciences appliquées / université, sans diplôme",
                        "two_year_degree": "Associate degree (2 ans)",
                        "four_year_degree": "Licence",
                        "masters": "Master",
                        "phd": "Doctorat/PhD"
                    }
                },
                "education_fr": {
                    "list": {
                        "high_school": "Collège-Lycée ou moins",
                        "baccalaureate": "Baccalauréat",
                        "vocational": "Autre type d'études supérieures",
                        "technical": "Bac +1",
                        "higher_technical": "Bac +2",
                        "bachelor": "Bac +3/+4 (Licence, Master 1)",
                        "master": "Master 2",
                        "phd": "Doctorat"
                    }
                },
                "education_in": {
                    "list": {
                        "some_secondary": "Études secondaires partielles ou niveau inférieur",
                        "secondary": "École secondaire",
                        "some_vocational": "Quelques années d'école professionnelle / collège technique",
                        "vocational": "École professionnelle / collège technique",
                        "some_university": "Quelques années d'études universitaires / supérieures",
                        "university": "Diplôme universitaire, diplôme avec mention",
                        "masters": "Master",
                        "phd": "Doctorat"
                    }
                },
                "education_ch": {
                    "list": {
                        "compulsory": "Scolarisation obligatoire / programme de transition",
                        "basic_vocational": "Enseignement professionnel de base / école d'enseignement général",
                        "technical": "Collège/université (technique), sans diplôme",
                        "higher_technical": "Formation technique ou professionnelle supérieure",
                        "bachelor": "Diplôme (technique) universitaire (Licence)",
                        "master": "Diplôme (technique) universitaire (Master)",
                        "phd": "Doctorat",
                        "some_compulsory": "Aucune ou jusqu'à 7 ans de scolarisation obligatoire"
                    }
                }
            },
            "household": {
                "householdSize": {
                    "question": "Combien de personnes vivent dans votre maison, y compris vous-même ?",
                    "list": {
                        "1": "1 personne",
                        "2": "2 personnes",
                        "3": "3 personnes",
                        "4": "4 personnes",
                        "5": "5 personnes",
                        "more_5": "Plus de 5 personnes"
                    },
                    "shortName": "Nombre de personnes qui vivent dans votre foyer"
                },
                "householdChildren": {
                    "question": "Combien d'enfants de moins de 18 ans vivent dans votre foyer ?",
                    "shortName": "Nombre d'enfants de moins de 18 ans dans votre foyer"
                },
                "pets": {
                    "question": "Parmi les animaux domestiques suivants, lesquels vivent dans votre maison ?",
                    "list": {
                        "cat": "Chat(s)",
                        "dog": "Chien(s)",
                        "bird": "Oiseau(x)",
                        "fish": "Poisson(s)",
                        "noPets": "Je n'ai pas d'animaux domestiques"
                    },
                    "shortName": "Les animaux domestiques qui vivent dans votre maison"
                },
                "ownRent": {
                    "question": "Quelle est la meilleure description de votre situation actuelle ?",
                    "list": {
                        "rented": "Locataire d'un appartement ou d'une maison",
                        "owned": "Propriétaire d'un appartement ou d'une maison",
                        "parents": "Je vis avec mes parents"
                    },
                    "shortName": "Situation actuelle"
                },
                "purchaseDecisionMaker": {
                    "question": "Dans votre foyer, pour lesquels des domaines suivants êtes-vous responsable ou partiellement responsable en termes de prise de décision ?",
                    "list": {
                        "internet": "Internet",
                        "tv": "Télévision",
                        "banking": "Banque",
                        "groceries": "Achat de produits alimentaires",
                        "automobile": "Automobile",
                        "mortgage": "Crédit immobilier",
                        "finance": "Finances",
                        "clothing": "Vêtements"
                    },
                    "shortName": "Domaines pour lesquels vous êtes responsable ou en partie responsable en termes de prise de décision dans votre foyer"
                },
                "firstChild_gender": {
                    "question": "Merci d’indiquer le genre de votre premier enfant de moins de 18 ans :",
                    "shortName": "Genre de votre premier enfant de moins de 18 ans"
                },
                "firstChild_birthday": {
                    "question": "Merci d'indiquer la date de naissance de votre premier enfant de moins de 18 ans :",
                    "shortName": "Date de naissance de votre premier enfant de moins de 18 ans"
                },
                "secondChild_gender": {
                    "question": "Merci d'indiquer le genre de votre deuxième enfant de moins de 18 ans :",
                    "shortName": "Genre de votre deuxième enfant de moins de 18 ans"
                },
                "secondChild_birthday": {
                    "question": "Merci d'indiquer la date de naissance de votre deuxième enfant de moins de 18 ans :",
                    "shortName": "Date de naissance de votre deuxième enfant de moins de 18 ans"
                },
                "thirdChild_gender": {
                    "question": "Merci d'indiquer le genre de votre troisième enfant de moins de 18 ans :",
                    "shortName": "Genre de votre troisième enfant de moins de 18 ans"
                },
                "thirdChild_birthday": {
                    "question": "Merci d'indiquer la date de naissance de votre troisième enfant de moins de 18 ans :",
                    "shortName": "Date de naissance de votre troisième enfant de moins de 18 ans"
                },
                "fourthChild_gender": {
                    "question": "Merci d'indiquer le genre de votre quatrième enfant de moins de 18 ans :",
                    "shortName": "Genre de votre quatrième enfant de moins de 18 ans"
                },
                "fourthChild_birthday": {
                    "question": "Merci d'indiquer la date de naissance de votre quatrième enfant de moins de 18 ans :",
                    "shortName": "Date de naissance de votre quatrième enfant de moins de 18 ans"
                },
                "fifthChild_gender": {
                    "question": "Merci d'indiquer le genre de votre cinquième enfant de moins de 18 ans :",
                    "shortName": "Genre de votre cinquième enfant de moins de 18 ans"
                },
                "fifthChild_birthday": {
                    "question": "Merci d'indiquer la date de naissance de votre cinquième enfant de moins de 18 ans :",
                    "shortName": "Date de naissance votre cinquième enfant de moins de 18 ans"
                }
            },
            "technology": {
                "mobilePlan": {
                    "question": "Quel type de forfait de téléphonie mobile avez-vous ?",
                    "list": {
                        "prepaid": "Prépayé",
                        "contract": "Contrat",
                        "noPhone": "Je n'ai pas de téléphone mobile"
                    },
                    "shortName": "Type de forfait de téléphonie mobile"
                },
                "electronicDevices": {
                    "question": "Parmi les produits électroniques suivants, quels sont ceux que vous possédez ?",
                    "list": {
                        "flatTv": "Télévision à écran plat",
                        "handheldConsole": "Console de jeu portable (Nintendo 2DS, Nintendo Switch)",
                        "stationaryConsole": "Console de jeu fixe (PlayStation, Xbox)",
                        "videoCamera": "Caméra vidéo",
                        "digitalCamera": "Appareil photo numérique",
                        "desktopPc": "Ordinateur de bureau PC / Mac",
                        "laptopPc": "Ordinateur portable PC / Mac",
                        "cellPhone": "Téléphone mobile / Smartphone",
                        "cordlessPhone": "Téléphone fixe sans fil",
                        "projector": "Projecteur",
                        "documentScanner": "Scanner de documents",
                        "cableTv": "TV par câble / TV par satellite",
                        "digitalTv": "Récepteur TV numérique",
                        "printer": "Imprimante",
                        "multipurposePrinter": "Imprimante multifonction (fax, imprimante, téléphone, etc.)",
                        "homeNetwork": "Réseau local / Internet sans fil (Wi-Fi)",
                        "surroundSystem": "Système Surround / Home Cinéma",
                        "digitalMediaReceiver": "Récepteur de médias numériques (ex. Apple TV, Roku)",
                        "tablet": "Tablette (ex. iPad)",
                        "ebook": "Lecteur de livres électroniques (ex. Kindle)"
                    },
                    "shortName": "Produits électroniques que vous possédez"
                }
            },
            "occupation": {
                "employment": {
                    "question": "Quelle est votre situation professionnelle actuelle / votre statut ?",
                    "list": {
                        "employed_full_time": "Employé à temps plein",
                        "employed_part_time": "Employé à temps partiel",
                        "self_employed": "Travailleur indépendant",
                        "small_business_owner": "Propriétaire d'une petite entreprise",
                        "contractor_or_consultant": "Entrepreneur ou Consultant",
                        "full_time_military": "Militaire actif",
                        "inactive_military": "Militaire inactif / Ancien combattant",
                        "homemaker": "Personne au foyer à plein temps",
                        "retired": "Retraité",
                        "student": "Étudiant",
                        "unable_or_disabled": "Handicapé en incapacité de travailler",
                        "looking_for_work": "Chômage temporaire"
                    },
                    "shortName": "Situation professionnelle / Statut"
                },
                "industry": {
                    "question": "Dans quel secteur d'activité travaillez-vous ?",
                    "list": {
                        "accounting": "Comptabilité",
                        "administrative": "Services administratifs et de support",
                        "advertising": "Publicité",
                        "agriculture": "Agriculture / Pêche",
                        "architecture": "Architecture",
                        "arts_recreation": "Arts, Spectacles et Loisirs",
                        "automotive": "Automobile",
                        "aviation": "Aviation",
                        "banking_finance": "Banque / Finance",
                        "biotech": "Bio-Tech",
                        "brokerage": "Courtage",
                        "chemicals_plastics_rubber": "Chimie / Plastiques / Caoutchouc",
                        "communications_information": "Communications / Information",
                        "computer_hardware": "Matériel informatique",
                        "computer_software": "Logiciels",
                        "computer_reseller": "Revendeur d'ordinateurs (logiciels / matériel)",
                        "construction": "Construction",
                        "consulting": "Conseil",
                        "consumer_electronics": "Électronique grand public",
                        "consumer_goods": "Biens de consommation emballés",
                        "education": "Éducation",
                        "energy_utilities": "Énergie / Services publics / Pétrole et gaz",
                        "engineering": "Ingénierie",
                        "environmental_services": "Services environnementaux",
                        "fashion_apparel": "Mode / Habillement",
                        "food_beverage": "Alimentation / Boissons",
                        "government_public_sector": "Gouvernement / Secteur public",
                        "healthcare": "Santé",
                        "hospitality_tourism": "Hôtellerie / Tourisme",
                        "human_resources": "Ressources humaines",
                        "information_technology": "Technologies de l'information",
                        "insurance": "Assurance",
                        "internet": "Internet",
                        "legal_law": "Juridique / Droit",
                        "management": "Gestion",
                        "manufacturing": "Industrie",
                        "market_research": "Études de marché",
                        "marketing_sales": "Marketing / Ventes",
                        "media_entertainment": "Médias / Divertissement",
                        "military": "Militaire",
                        "non_profit_social_services": "Services sociaux / Organisme à but non lucratif",
                        "personal_services": "Services à la personne",
                        "pharmaceuticals": "Industrie pharmaceutique",
                        "printing_publishing": "Imprimerie et Édition",
                        "professional_services": "Services professionnels",
                        "public_administration": "Administration publique",
                        "public_relations": "Relations publiques",
                        "real_estate_property": "Immobilier / Propriété",
                        "retail_wholesale_trade": "Commerce de détail / Commerce de gros",
                        "scientific_technical_services": "Services scientifiques ou techniques",
                        "security": "Sécurité",
                        "shipping_distribution": "Livraison / Distribution",
                        "telecommunications": "Télécommunications",
                        "transportation": "Transport",
                        "user_experience_research": "Recherche utilisateur"
                    },
                    "shortName": "Secteur d'activité"
                },
                "jobDepartment": {
                    "question": "Dans quel département travaillez-vous principalement au sein de votre organisation ?",
                    "list": {
                        "admin": "Administration / Personnel général",
                        "customer_service": "Service client / Service clientèle",
                        "executive": "Direction générale / C-Level",
                        "finance_accounting": "Finance / Comptabilité",
                        "human_resources": "Ressources humaines",
                        "legal": "Juridique / Droit",
                        "marketing": "Marketing",
                        "operations": "Opérations",
                        "procurement": "Approvisionnement",
                        "product_management": "Gestion des produits",
                        "sales": "Ventes / Développement commercial",
                        "technology_hardware": "Développement de technologies matérielles (pas seulement informatique)",
                        "technology_software": "Développement de technologies logicielles (pas seulement informatique)",
                        "technology_implementation": "Mise en œuvre des technologies",
                        "other": "Autre"
                    },
                    "shortName": "Département d'entreprise"
                },
                "jobTitle": {
                    "question": "Quel est le titre ou le niveau de responsabilité de votre poste ?",
                    "list": {
                        "top_tier": "C-Level (ex. PDG, directeur financier), propriétaire, partenaire, président",
                        "vp_tier": "Vice-président (EVP, SVP, AVP, VP)",
                        "director_tier": "Directeur (group director, directeur principal, directeur)",
                        "management_tier": "Manager (group manager, manager principal, manager, program manager)",
                        "analyst": "Analyste",
                        "associate": "Assistant ou Junior",
                        "administrative": "Administratif (personnel de bureau ou de soutien)",
                        "individual_contributor": "Contributeur individuel",
                        "contractor": "Contractuel",
                        "consultant": "Consultant",
                        "intern": "Stagiaire",
                        "volunteer": "Bénévole",
                        "other": "Autre"
                    },
                    "shortName": "Intitulé du poste"
                },
                "decisionMaker": {
                    "question": "Parmi les départements/produits suivants, sur lesquels avez-vous une influence ou un pouvoir de décision en matière de dépenses/achats ?",
                    "list": {
                        "itHardware": "Matériel informatique",
                        "itSoftware": "Logiciels",
                        "printers": "Imprimantes et photocopieurs",
                        "financial": "Département financier",
                        "humanResources": "Ressources humaines",
                        "officeSupplies": "Fournitures de bureau",
                        "corporateTravel": "Voyages d'affaires",
                        "telecommunications": "Télécommunications",
                        "sales": "Ventes",
                        "shipping": "Expédition",
                        "operations": "Opérations",
                        "legalServices": "Services juridiques",
                        "marketing": "Marketing/Publicité",
                        "security": "Sécurité",
                        "foodServices": "Services alimentaires",
                        "autoleasing": "Location/achat de véhicules"
                    },
                    "shortName": "Services/produits sur lesquels vous avez une influence ou un pouvoir de décision en matière de dépenses/achats."
                },
                "companySize": {
                    "question": "Combien d'employés environ travaillent dans votre entreprise (tous sites confondus) ?",
                    "shortName": "Nombre d'employés de votre organisation"
                }
            },
            "hobbiesAndInterests": {
                "hobbies": {
                    "question": "Quels sont vos passe-temps et centres d'intérêt ?",
                    "list": {
                        "artsCrafts": "Arts et artisanat",
                        "boating": "Navigation de plaisance",
                        "camping": "Camping",
                        "cooking": "Cuisine",
                        "golf": "Golf",
                        "healthFitness": "Santé et fitness",
                        "huntingFishing": "Chasse / Pêche",
                        "interiorDecorating": "Décoration intérieure / Rénovation",
                        "teamSports": "Sports d'équipe",
                        "playingMusic": "Jouer de la musique",
                        "videogames": "Jeux vidéo",
                        "reading": "Lecture",
                        "skiing": "Ski",
                        "technology": "Technologie / Ordinateurs",
                        "travel": "Voyage",
                        "tvSports": "Regarder le sport à la télévision"
                    },
                    "shortName": "Passe-temps et centres d'intérêt"
                },
                "socialMedia": {
                    "question": "Parmi les plateformes de réseaux et médias sociaux suivantes, lesquelles utilisez-vous régulièrement ?",
                    "shortName": "Les plateformes de réseaux et médias sociaux que vous utilisez régulièrement"
                },
                "streamingMovies": {
                    "question": "En moyenne, à quelle fréquence téléchargez-vous des films ou regardez-vous des films en streaming depuis chez vous ?",
                    "list": {
                        "less1": "Moins d'une fois par mois",
                        "1": "Une fois par mois",
                        "2": "Deux fois par mois",
                        "3": "Trois fois par mois",
                        "4": "Quatre fois par mois",
                        "5": "Cinq fois par mois",
                        "none": "Je ne télécharge pas de films / ne regarde pas de films en streaming"
                    },
                    "shortName": "Fréquence de streaming ou de téléchargement de films"
                },
                "gambling": {
                    "question": "À quel genre de paris jouez-vous ?",
                    "list": {
                        "onlineSports": "Paris sportifs en ligne",
                        "onlineLottery": "Loterie / Jeux à gratter en ligne",
                        "onlinePoker": "Poker / Jeux de casino en ligne",
                        "offlineSports": "Paris sportifs hors ligne",
                        "offlineLottery": "Loterie / Jeux à gratter hors ligne",
                        "bingo": "Bingo",
                        "casinoPoker": "Casino (poker, blackjack, roulette, etc.)",
                        "casinoSlot": "Machines à sous au casino",
                        "horseTrack": "Paris hippiques",
                        "carRace": "Paris sur les sports automobiles",
                        "none": "Je ne parie pas du tout"
                    },
                    "shortName": "Types de jeux d'argent auxquels vous participez"
                }
            },
            "financial": {
                "financialProduct": {
                    "question": "Parmi les produits financiers suivants, lesquels possédez-vous ?",
                    "list": {
                        "creditCard": "Carte de crédit",
                        "checkingAccount": "Compte courant",
                        "savingsAccount": "Compte d'épargne",
                        "personalLoan": "Emprunt personnel",
                        "mortgage": "Prêt immobilier"
                    },
                    "shortName": "Produits financiers que vous possédez"
                },
                "investments_us": {
                    "list": {
                        "none": "Je n'ai pas de compte d'épargne/compte titres",
                        "401k": "Plan 401(k)",
                        "ira": "Compte individuel d'épargne retraite (IRA/Roth)",
                        "bonds": "Obligations",
                        "deposit": "Certificat de dépôt",
                        "mutualFunds": "Fonds mutuels"
                    }
                },
                "investments_gb": {
                    "list": {
                        "none": "Je n'ai pas de compte épargne ou de compte titres",
                        "personalPension": "Pension personnelle",
                        "workplacePension": "Pension professionnelle",
                        "unitTrusts": "Fonds communs de placement",
                        "oeic": "OEIC - Société de fonds mutuels",
                        "etf": "ETF Securities (ou fonds négociés en bourse)",
                        "investmentTrusts": "Fiducie de placement",
                        "fixedIncomeProducts": "Produits à revenu fixe"
                    }
                }
            },
            "healthAndFitness": {
                "diagnosed_ailments": {
                    "question": "Vous a-t-on diagnostiqué l'un des troubles ou maladies suivants ?",
                    "list": {
                        "acne": "Acné",
                        "add_adhd": "TDA/TDAH",
                        "allergies": "Allergies (hors rhume des foins)",
                        "alzheimers": "Alzheimer",
                        "anemia": "Anémie",
                        "angina": "Angine",
                        "anxiety": "Anxiété",
                        "arrhythmia": "Arythmie / Fibrillation auriculaire",
                        "arthritis": "Arthrite",
                        "asthma": "Asthme",
                        "backPain": "Mal de dos",
                        "bipolar": "Trouble bipolaire",
                        "bloodDisorders": "Maladie du sang (hors cancer)",
                        "bronchitits": "Bronchite",
                        "cancer": "Cancer",
                        "cardiovascular": "Maladie cardiovasculaire",
                        "carpalTunnel": "Syndrome du canal carpien",
                        "chronicFatigue": "Syndrome de fatigue chronique",
                        "chronicKidney": "Insuffisance rénale chronique",
                        "chronicLymphocytic": "Leucémie lymphoïde chronique",
                        "copd": "Bronchopneumopathie chronique obstructive",
                        "cirrhosis": "Cirrhose",
                        "colitis": "Colite",
                        "constipation": "Constipation",
                        "crohns": "Maladie de Crohn",
                        "cystic": "Fibrose kystique",
                        "dementia": "Démence",
                        "dental": "Problèmes dentaires",
                        "depresssion": "Dépression",
                        "diabetes1": "Diabète de type 1",
                        "diabetes2": "Diabète de type 2",
                        "diarrhea": "Diarrhée",
                        "eczema": "Eczéma",
                        "emphysema": "Emphysème",
                        "endometriosis": "Endométriose",
                        "epilepsy": "Épilepsie",
                        "erectileDysfunction": "Dysfonction érectile (DE)",
                        "fibromyalgia": "Fibromyalgie",
                        "foodIntolerances": "Intolérances alimentaires",
                        "gerd": "Reflux gastro-œsophagien (RGO)",
                        "gastroenteritis": "Gastro-entérite",
                        "gout": "Goutte",
                        "hemophilia": "Hémophilie",
                        "hemorrhoids": "Hémorroïdes",
                        "hayFever": "Rhume des foins",
                        "heartConditions": "Problèmes cardiaques (hors insuffisance cardiaque)",
                        "heartFailure": "Insuffisance cardiaque",
                        "hepatitis": "Hépatite",
                        "cholesterol": "Cholestérol élevé",
                        "aids": "VIH - SIDA",
                        "hypertension": "Hypertension",
                        "hypothyroidism": "Hypothyroïdie",
                        "impotence": "Impuissance",
                        "infertility": "Infertilité",
                        "irritableBowelSyndrome": "Syndrome de l'intestin irritable",
                        "jointReplacement": "Remplacement d'articulation",
                        "kidneyFailure": "Insuffisance rénale",
                        "liverCirrhosis": "Cirrhose hépatique",
                        "liverDisorders": "Maladie du foie (hors cancer et cirrhose)",
                        "lupus": "Lupus",
                        "luymeDisease": "Maladie de Lyme",
                        "menopause": "Ménopause",
                        "migraine": "Migraine",
                        "motorNeuronDisease": "Maladie de Charcot",
                        "multipleSclerosis": "Sclérose en plaques",
                        "obesity": "Obésité",
                        "osteoarthritis": "Arthrose",
                        "osteoporosis": "Ostéoporose",
                        "overactiveBladder": "Vessie hyperactive",
                        "parkinons": "Maladie de Parkinson",
                        "pneumonia": "Pneumonie",
                        "prematureEjaculation": "Éjaculation précoce",
                        "psoriasis": "Psoriasis",
                        "reflux": "Reflux",
                        "restlessLegSyndrome": "Syndrome des jambes sans repos",
                        "rheumatoidArthritis": "Polyarthrite rhumatoïde",
                        "schizophrenia ": "Schizophrénie",
                        "shingles ": "Zona",
                        "sinusitis": "Sinusite",
                        "sleepingDisorder": "Troubles du sommeil",
                        "smoking": "Addiction au tabac",
                        "stroke": "Attaque",
                        "substanceAbuse": "Consommation abusive de drogues/alcool",
                        "syphilis": "Syphilis",
                        "thyroidProblems": "Problèmes de thyroïde",
                        "tuberculosis ": "Tuberculose",
                        "ulcerativeColitis": "Rectocolite hémorragique",
                        "ulcers": "Ulcère",
                        "urinaryIncontinence": "Incontinence urinaire"
                    },
                    "shortName": "Maladies/conditions/troubles qui ont été diagnostiqués chez vous"
                }
            },
            "travel": {
                "travelFlights": {
                    "question": "À quelle fréquence voyagez-vous en avion ?",
                    "list": {
                        "everyMonth": "Une fois par mois ou plus",
                        "every2-4Months": "Une fois tous les 2 à 4 mois",
                        "twiceYear": "Deux fois par an",
                        "onceYear": "Une fois par an"
                    },
                    "shortName": "Fréquence de vos voyages en avion"
                },
                "flightPurpose": {
                    "question": "Pour quels motifs voyagez-vous en avion ?",
                    "list": {
                        "business": "Travail",
                        "leisure": "Loisir",
                        "both": "Travail et loisir",
                        "neither": "Je ne voyage pas en avion"
                    },
                    "shortName": "Motifs de vos voyages en avion"
                },
                "flightDestination": {
                    "question": "Lorsque vous prenez l'avion, quels types de vols prenez-vous ?",
                    "list": {
                        "domestic": "Intérieurs",
                        "international": "Internationaux",
                        "both": "Intérieurs et internationaux",
                        "neither": "Je préfère ne pas répondre"
                    },
                    "shortName": "Types de vols que vous prenez"
                },
                "domesticAirlines_us": {
                    "question": "Avec quelles compagnies aériennes nationales avez-vous voyagé au cours des 12 derniers mois ?",
                    "list": {
                        "none": "Je n'ai pas pris de vol intérieur au cours des 12 derniers mois"
                    },
                    "shortName": "Compagnies aériennes nationales avec lesquelles vous avez volé au cours des 12 derniers mois"
                },
                "internationalAirlines": {
                    "question": "Avec quelles compagnies aériennes internationales avez-vous voyagé au cours des 12 derniers mois ?",
                    "list": {
                        "none": "Je n'ai pas pris de vol international au cours des 12 derniers mois"
                    },
                    "shortName": "Compagnies aériennes internationales avec lesquelles vous avez volé au cours des 12 derniers mois"
                },
                "accomodationType": {
                    "question": "Quel type d'hébergement avez-vous utilisé pour vos déplacements au cours de l’année passée ?",
                    "list": {
                        "houseRental": "Location de maison (AirBnB & VRBO)",
                        "bedBreakfast": "Chambre et petit déjeuner (Bed & Breakfast)",
                        "campground": "Camping / Terrain de camping-cars",
                        "hostel": "Auberge / Auberge de jeunesse",
                        "hotel": "Hôtel",
                        "motel": "Motel",
                        "personalVacationHome": "Résidence de vacances personnelle",
                        "timeshare": "Location en temps partagé"
                    },
                    "shortName": "Type d'hébergement que vous avez utilisé au cours de l'année écoulée"
                },
                "hotelLoyalty": {
                    "question": "Êtes-vous membre de l'un des programmes de fidélité hôteliers suivants ?",
                    "shortName": "Programmes de fidélité d'hôtels dont vous êtes membre"
                }
            }
        },
        "generic": {
            "education": {
                "question": "Quel est le niveau d'études le plus élevé que vous ayez atteint ?",
                "shortName": "Niveau d'études le plus élevé"
            },
            "householdIncome": {
                "question": "Quel est le revenu annuel total combiné de tous les membres de votre foyer avant impôts ?",
                "shortName": "Somme totale des revenus annuels de tous les membres de votre foyer (avant impôts)"
            },
            "mobileCarrier": {
                "question": "Lequel de ces opérateurs est celui du téléphone mobile que vous utilisez le plus souvent ?",
                "shortName": "Opérateur du téléphone mobile que vous utilisez le plus souvent"
            },
            "companyRevenue": {
                "question": "Quel est le chiffre d'affaires annuel approximatif de votre entreprise ?",
                "shortName": "Revenu annuel approximatif de votre entreprise"
            },
            "subscriptions": {
                "question": "Parmi les services suivants, auxquels avez-vous souscrit un abonnement ?",
                "shortName": "Services auxquels vous avez souscrit"
            },
            "investments": {
                "question": "Parmi les comptes d'épargne et/ou comptes titres suivants, lesquels possédez-vous ?",
                "realEstate": "Bien immobilier",
                "savingsAccount": "Compte d'épargne",
                "shares": "Actions",
                "shortName": "Comptes d'épargne ou comptes titres que vous possédez"
            },
            "investableAssets": {
                "question": "À combien s'élève l'épargne de votre foyer (hors propriété de votre logement) ?",
                "shortName": "Montant approximatif de l'épargne de votre foyer (hors propriété du logement)"
            },
            "airlineLoyalty": {
                "question": "Êtes-vous membre de l'un des programmes de fidélité des compagnies aériennes suivantes ?",
                "list": {
                    "none": "Je ne suis membre d'aucun programme de fidélité de compagnie aérienne"
                },
                "shortName": "Programmes de fidélité de compagnies aériennes dont vous êtes membre"
            },
            "hotelLoyalty": {
                "list": {
                    "none": "Je ne suis membre d'aucun programme de fidélité d'hôtel"
                }
            },
            "ethnicity": {
                "question": "Quelle est votre origine ethnique ?",
                "shortName": "Origine ethnique"
            },
            "noPhone": {
                "noPhone": "Je n'ai pas de téléphone mobile"
            },
            "socialMedia": {
                "question": "Parmi les plateformes de réseaux et médias sociaux suivantes, lesquelles utilisez-vous régulièrement ?",
                "shortName": "Les plateformes de réseaux et médias sociaux que vous utilisez régulièrement"
            }
        }
    },
    "izPanel": {
        "common": {
            "demographics": {
                "billion": "milliard"
            }
        }
    }
}